badgie/__init__.py
badgie/__main__.py
badgie/_version.py
badgie/cli.py
badgie/constants.py
badgie/models.py
badgie/parser.py
badgie/project.py
badgie/py.typed
badgie/tokens.py
badgie/utils.py
badgie/badges/__init__.py
badgie/badges/_base.py
badgie/badges/cici_tools.py
badgie/badges/gitlab.py
badgie/badges/precommit.py
badgie/badges/prettier.py
badgie/badges/python.py
badgie/badges/saferatday0.py
badgie/finders/__init__.py
badgie/finders/files.py
badgie/finders/gitlab.py
badgie/finders/pre_commit_config.py
badgie/finders/remotes.py
badgie-0.14.4.dist-info/licenses/LICENSE
badgie-0.14.4.dist-info/licenses/NOTICE
badgie-0.14.4.dist-info/METADATA
badgie-0.14.4.dist-info/WHEEL
badgie-0.14.4.dist-info/entry_points.txt
badgie-0.14.4.dist-info/top_level.txt
badgie-0.14.4.dist-info/RECORD
