Metadata-Version: 2.4
Name: badgie
Version: 0.14.4
Summary: Add all the badges with Badgie!
Author-email: Digital Safety Research Institute <contact@dsri.org>
License: Apache-2.0
Project-URL: Home, https://gitlab.com/saferatday0/badgie
Project-URL: Issues, https://gitlab.com/saferatday0/badgie/-/issues
Keywords: badge,template,markdown
Classifier: Development Status :: 3 - Alpha
Classifier: Environment :: Console
Classifier: Intended Audience :: Developers
Classifier: Programming Language :: Python :: 3
Classifier: Programming Language :: Python :: 3.9
Classifier: Programming Language :: Python :: 3.10
Classifier: Programming Language :: Python :: 3.11
Classifier: Programming Language :: Python :: 3.12
Classifier: Topic :: Software Development :: Build Tools
Classifier: Topic :: Software Development :: Documentation
Classifier: Topic :: Software Development :: Quality Assurance
Classifier: Topic :: Utilities
Requires-Python: >=3.9
License-File: LICENSE
License-File: NOTICE
Requires-Dist: attrs
Requires-Dist: certifi
Requires-Dist: charset-normalizer
Requires-Dist: idna
Requires-Dist: python-gitlab
Requires-Dist: pyyaml
Requires-Dist: requests
Requires-Dist: requests-toolbelt
Requires-Dist: termcolor
Requires-Dist: urllib3
Dynamic: license-file
